utils/__init__.py
utils/_internal/__init__.py
utils/_internal/depends.py
utils/exceptions/Js_exception.py
utils/exceptions/__init__.py
utils/js/JsClass.py
utils/js/__init__.py
utils/networking/__init__.py
utils/networking/downloadAdapter.py
utils/system/__init__.py
utils/system/paths.py
utils/thread_helpers/__init__.py
utils/thread_helpers/animations.py
utils_s-3.8.dist-info/LICENSE.txt
utils_s-3.8.dist-info/METADATA
utils_s-3.8.dist-info/WHEEL
utils_s-3.8.dist-info/top_level.txt
utils_s-3.8.dist-info/RECORD
