Metadata-Version: 2.1
Name: utils-s
Version: 3.8
Summary: Utility functions
Home-page: https://github.com/The-Sal/utils/
Author: Sal Faris
License-File: LICENSE.txt
